seller_stats/__init__.py
seller_stats/base.py
seller_stats/category_list_updates.py
seller_stats/category_stats.py
seller_stats/category_updates.py
seller_stats/exceptions.py
seller_stats/formatters.py
seller_stats/loaders.py
seller_stats/sales_stats.py
seller_stats/transformers.py
seller_stats/utils/__init__.py
seller_stats/utils/formatters.py
seller_stats/utils/loaders.py
seller_stats/utils/stats.py
seller_stats/utils/transformers.py
tests/__init__.py
tests/_test_category_chages_notifications.py
tests/conftest.py
tests/test_category_stats.py
tests/test_formatters.py
tests/test_loaders.py
tests/test_transformers.py
tests/test_utils_formatters.py
tests/test_utils_loaders.py
tests/test_utils_stats.py
tests/test_utils_transformers.py
seller_stats-0.3.1.dist-info/LICENCE
seller_stats-0.3.1.dist-info/METADATA
seller_stats-0.3.1.dist-info/WHEEL
seller_stats-0.3.1.dist-info/top_level.txt
seller_stats-0.3.1.dist-info/RECORD
